codex_bridge-1.2.3.dist-info/licenses/LICENSE
src/__init__.py
src/__main__.py
src/mcp_server.py
codex_bridge-1.2.3.dist-info/METADATA
codex_bridge-1.2.3.dist-info/WHEEL
codex_bridge-1.2.3.dist-info/entry_points.txt
codex_bridge-1.2.3.dist-info/top_level.txt
codex_bridge-1.2.3.dist-info/RECORD
