Metadata-Version: 2.4
Name: codex-bridge
Version: 1.2.3
Summary: Lightweight MCP server bridging Claude Code to OpenAI Codex via official CLI
Author-email: Shelakh <info@shelakh.com>
License-Expression: MIT
Project-URL: Homepage, https://github.com/shelakh/codex-bridge
Project-URL: Repository, https://github.com/shelakh/codex-bridge
Project-URL: Issues, https://github.com/shelakh/codex-bridge/issues
Keywords: mcp,codex,openai,ai,coding,assistant
Classifier: Development Status :: 5 - Production/Stable
Classifier: Intended Audience :: Developers
Classifier: Programming Language :: Python :: 3
Classifier: Programming Language :: Python :: 3.10
Classifier: Programming Language :: Python :: 3.11
Classifier: Programming Language :: Python :: 3.12
Classifier: Topic :: Software Development :: Libraries :: Python Modules
Classifier: Topic :: Scientific/Engineering :: Artificial Intelligence
Requires-Python: >=3.10
License-File: LICENSE
Requires-Dist: mcp>=1.0.0
Dynamic: license-file
